{"cameraMode":{"drawMode":0,"name":"Shaded","section":"Shading Mode"},"sceneLighting":true,"audioPlay":false,"sceneViewState":{"showFog":true,"showMaterialUpdate":false,"showSkybox":true,"showFlares":true,"showImageEffects":true,"showParticleSystems":true},"in2DMode":false,"pivot":{"x":126.65507507324219,"y":163.94650268554688,"z":-2.367950439453125},"rotation":{"x":-0.0008848911966197193,"y":0.9988085627555847,"z":0.0446665920317173,"w":0.019780198112130166},"size":200.71018981933595,"orthographic":false}